imgui/__init__.pyi
pyimgui_stubs-0.0.2.dist-info/METADATA
pyimgui_stubs-0.0.2.dist-info/WHEEL
pyimgui_stubs-0.0.2.dist-info/top_level.txt
pyimgui_stubs-0.0.2.dist-info/RECORD
